CHANGELOG.md
LICENSE
MANIFEST.in
README.md
README.txt
setup.py
wagtail_global_settings/__init__.py
wagtail_global_settings/context_processors.py
wagtail_global_settings/models.py
wagtail_global_settings/permissions.py
wagtail_global_settings/urls.py
wagtail_global_settings/wagtail_hooks.py
wagtail_global_settings.egg-info/PKG-INFO
wagtail_global_settings.egg-info/SOURCES.txt
wagtail_global_settings.egg-info/dependency_links.txt
wagtail_global_settings.egg-info/requires.txt
wagtail_global_settings.egg-info/top_level.txt
wagtail_global_settings/templates/wagtail_global_settings/choose.html
wagtail_global_settings/templates/wagtail_global_settings/choose_site.html
wagtail_global_settings/templates/wagtail_global_settings/choose_site_setting.html
wagtail_global_settings/templates/wagtail_global_settings/edit.html
wagtail_global_settings/templates/wagtail_global_settings/edit_site_setting.html
wagtail_global_settings/templatetags/__init__.py
wagtail_global_settings/templatetags/global_settings_tags.py
wagtail_global_settings/templatetags/site_settings_tags.py
wagtail_global_settings/views/__init__.py
wagtail_global_settings/views/global_settings.py
wagtail_global_settings/views/site_settings.py