Metadata-Version: 1.1
Name: wagtail-global-settings
Version: 0.1.3
Summary: Global settings editor for Wagtail using django-solo
Home-page: https://bitbucket.org/jordanmarkov/wagtail-global-settings
Author: Jordan Markov
Author-email: jmarkov@gmail.com
License: BSD License
Download-URL: https://bitbucket.org/jordanmarkov/wagtail-global-settings/get/0.1.3.tar.gz
Platform: UNKNOWN
Classifier: Environment :: Web Environment
Classifier: Framework :: Django
Classifier: Intended Audience :: Developers
Classifier: License :: OSI Approved :: BSD License
Classifier: Operating System :: OS Independent
Classifier: Programming Language :: Python
Classifier: Topic :: Internet :: WWW/HTTP
Classifier: Topic :: Internet :: WWW/HTTP :: Dynamic Content
